{"events":[{"params":[false,true,0],"name":"Alt Animation Toggle","time":0},{"params":["15",true,false,true,true,true,"sine","In"],"name":"Bar Cinematic","time":0},{"params":[300,-490,false,4,"CLASSIC","In",false],"time":0,"name":"Camera Position"},{"params":[-16777216,"4",false,"camGame"],"time":0,"name":"fade"},{"params":[615,60,true,120,"quad","InOut",false],"time":1016.94915254237,"name":"Camera Position"},{"params":["cube","InOut","15","0.5"],"name":"Cam Zoom","time":1144.06779661017},{"params":[0,true,8,"circ","In"],"time":15254.2372881356,"name":"Camera Movement"},{"params":["circ","In","1.2","0.515"],"time":15254.2372881356,"name":"Cam Zoom"},{"params":[0,"trans",true,"NONE"],"time":15762.7118644068,"name":"Play Animation"},{"params":[false,false,0],"time":16271.186440678,"name":"Alt Animation Toggle"},{"params":[false,-11206634,8,"camGame"],"name":"Camera Flash","time":16271.186440678},{"params":["5",false,false,false,false,false,"back","Out"],"name":"Bar Cinematic","time":16271.186440678},{"params":[0,true,4,"CLASSIC","In"],"time":16271.186440678,"name":"Camera Movement"},{"params":["quint","Out","1","0.525"],"time":20338.9830508475,"name":"Cam Zoom"},{"params":[1,true,4,"CLASSIC","In"],"time":24406.7796610169,"name":"Camera Movement"},{"params":["quint","Out","2","0.7"],"time":24406.7796610169,"name":"Cam Zoom"},{"params":["quint","Out","1","0.725"],"name":"Cam Zoom","time":28474.5762711864},{"params":["quint","Out","1","0.72"],"time":30508.4745762712,"name":"Cam Zoom"},{"params":["quint","Out","1","0.715"],"name":"Cam Zoom","time":31016.9491525424},{"params":["quint","Out","1","0.71"],"time":31525.4237288136,"name":"Cam Zoom"},{"params":["quint","Out","1","0.7"],"name":"Cam Zoom","time":32033.8983050847},{"params":[0,true,16,"CLASSIC","InOut"],"name":"Camera Movement","time":32542.3728813559},{"params":["quint","Out","1","0.5"],"time":32542.3728813559,"name":"Cam Zoom"},{"params":["quad","Out","1","1.4"],"time":32542.3728813559,"name":"Beat Flash"},{"params":["sine","Out","1","0.3"],"time":32542.3728813559,"name":"black disto 2"},{"params":["quint","Out","1","0.525"],"time":34576.2711864407,"name":"Cam Zoom"},{"params":["quad","Out","1","1.4"],"time":34576.2711864407,"name":"Beat Flash"},{"params":[1,true,16,"CLASSIC","InOut"],"name":"Camera Movement","time":36610.1694915254},{"params":["quint","Out","1","0.7"],"time":36610.1694915254,"name":"Cam Zoom"},{"params":["quad","Out","1","1.4"],"time":36610.1694915254,"name":"Beat Flash"},{"params":["quint","Out","1","0.725"],"name":"Cam Zoom","time":38644.0677966102},{"params":["quad","Out","1","1.4"],"time":38644.0677966102,"name":"Beat Flash"},{"params":["quad","Out","1","1.4"],"time":40677.9661016949,"name":"Beat Flash"},{"params":["sine","InOut","2.5","0.4"],"time":40677.9661016949,"name":"Cam Zoom"},{"params":[0,true,32,"CLASSIC","In"],"time":40677.9661016949,"name":"Camera Movement"},{"params":["quad","Out","1","1.4"],"time":41694.9152542373,"name":"Beat Flash"},{"params":["quad","Out","1","1.4"],"name":"Beat Flash","time":42711.8644067797},{"params":["quad","Out","1","1.4"],"time":43728.813559322,"name":"Beat Flash"},{"params":[true,2.8,16,"linear","In",false],"name":"Scroll Speed Change","time":44745.7627118644},{"params":["quad","Out","1","1.4"],"time":44745.7627118644,"name":"Beat Flash"},{"params":["quad","Out","1","1.4"],"name":"Beat Flash","time":45254.2372881356},{"params":["quad","Out","1","1.4"],"time":45762.7118644068,"name":"Beat Flash"},{"params":["quad","Out","1","1.4"],"time":46271.186440678,"name":"Beat Flash"},{"params":[0,"saut",true,"NONE"],"time":46800.8474576271,"name":"Play Animation"},{"params":["quint","Out","1","0.45"],"time":46800.8474576271,"name":"Cam Zoom"},{"params":[0,"bas",true,"NONE"],"time":48569.9152542373,"name":"Play Animation"},{"params":["0.005","2"],"time":48686.4406779661,"name":"Shake"},{"params":[false,-1,8,"camGame"],"name":"Camera Flash","time":48813.5593220339},{"params":["quint","Out","1","0.4"],"time":48813.5593220339,"name":"Cam Zoom"},{"params":["sine","Out","1","0"],"time":48813.5593220339,"name":"black disto 2"},{"params":[1,true,4,"CLASSIC","In"],"name":"Camera Movement","time":52881.3559322034},{"params":["quint","Out","1","0.7"],"time":52881.3559322034,"name":"Cam Zoom"},{"params":["quint","Out","1","0.675"],"time":56779.6610169491,"name":"Cam Zoom"},{"params":[0,true,4,"CLASSIC","In"],"name":"Camera Movement","time":56949.1525423729},{"params":["quint","Out","1","0.4"],"time":56949.1525423729,"name":"Cam Zoom"},{"params":[1,true,4,"CLASSIC","In"],"name":"Camera Movement","time":61016.9491525424},{"params":["quint","Out","1","0.7"],"time":61016.9491525424,"name":"Cam Zoom"},{"params":["quint","Out","1","0.675"],"time":62033.8983050847,"name":"Cam Zoom"},{"params":["quint","Out","1","0.65"],"name":"Cam Zoom","time":63050.8474576271},{"params":["quint","Out","1","0.7"],"name":"Cam Zoom","time":64067.7966101695},{"params":[0,true,8,"expo","In"],"time":64067.7966101695,"name":"Camera Movement"},{"params":["expo","In","0.6","0.4"],"time":64576.2711864407,"name":"Cam Zoom"},{"params":[0,true,4,"CLASSIC","In"],"name":"Camera Movement","time":65084.7457627119},{"params":["quad","Out","1","1.4"],"time":65084.7457627119,"name":"Beat Flash"},{"params":[-1,"1",false,"camGame"],"time":65084.7457627119,"name":"fade"},{"params":["quad","Out","1","1.4"],"time":65593.2203389831,"name":"Beat Flash"},{"params":[0.01,"camGame"],"time":65593.2203389831,"name":"Add Camera Zoom"},{"params":["quad","Out","1","1.4"],"name":"Beat Flash","time":66101.6949152542},{"params":[0.01,"camGame"],"name":"Add Camera Zoom","time":66101.6949152542},{"params":["quad","Out","1","1.4"],"time":66610.1694915254,"name":"Beat Flash"},{"params":[0.01,"camGame"],"time":66610.1694915254,"name":"Add Camera Zoom"},{"params":["quad","Out","1","1.4"],"name":"Beat Flash","time":67118.6440677966},{"params":["quad","Out","1","1.4"],"time":67627.1186440678,"name":"Beat Flash"},{"params":[0.01,"camGame"],"time":67627.1186440678,"name":"Add Camera Zoom"},{"params":["quad","Out","1","1.4"],"name":"Beat Flash","time":68135.593220339},{"params":[0.01,"camGame"],"name":"Add Camera Zoom","time":68135.593220339},{"params":["quad","Out","1","1.4"],"time":68644.0677966102,"name":"Beat Flash"},{"params":[0.01,"camGame"],"time":68644.0677966102,"name":"Add Camera Zoom"},{"params":[1,true,4,"CLASSIC","In"],"name":"Camera Movement","time":69152.5423728814},{"params":["quint","Out","1","0.7"],"time":69152.5423728814,"name":"Cam Zoom"},{"params":["quad","Out","1","1.4"],"time":69152.5423728814,"name":"Beat Flash"},{"params":["quad","Out","1","1.4"],"name":"Beat Flash","time":69661.0169491525},{"params":[0.01,"camGame"],"name":"Add Camera Zoom","time":69661.0169491525},{"params":["quad","Out","1","1.4"],"time":70169.4915254237,"name":"Beat Flash"},{"params":[0.01,"camGame"],"time":70169.4915254237,"name":"Add Camera Zoom"},{"params":["quad","Out","1","1.4"],"name":"Beat Flash","time":70677.9661016949},{"params":[0.01,"camGame"],"name":"Add Camera Zoom","time":70677.9661016949},{"params":["quint","Out","1","0.675"],"time":71186.4406779661,"name":"Cam Zoom"},{"params":["quad","Out","1","1.4"],"time":71186.4406779661,"name":"Beat Flash"},{"params":["quad","Out","1","1.4"],"time":71694.9152542373,"name":"Beat Flash"},{"params":[0.01,"camGame"],"time":71694.9152542373,"name":"Add Camera Zoom"},{"params":["quint","Out","1","0.7"],"name":"Cam Zoom","time":72203.3898305085},{"params":["quad","Out","1","1.4"],"time":72203.3898305085,"name":"Beat Flash"},{"params":[0.01,"camGame"],"time":72203.3898305085,"name":"Add Camera Zoom"},{"params":["quint","Out","1","0.725"],"time":72711.8644067797,"name":"Cam Zoom"},{"params":["quad","Out","1","1.4"],"time":72711.8644067797,"name":"Beat Flash"},{"params":[0.01,"camGame"],"time":72711.8644067797,"name":"Add Camera Zoom"},{"params":["quint","Out","1","0.7"],"name":"Cam Zoom","time":73220.3389830509},{"params":["quad","Out","1","1.4"],"time":73220.3389830509,"name":"Beat Flash"},{"params":[0,false,4,"CLASSIC","In"],"name":"Camera Movement","time":73728.813559322},{"params":["quint","Out","0.01","0.4"],"time":73728.813559322,"name":"Cam Zoom"},{"params":[0.01,"camGame"],"time":73728.813559322,"name":"Add Camera Zoom"},{"params":["quad","Out","1","1.4"],"time":73728.813559322,"name":"Beat Flash"},{"params":[1,false,4,"CLASSIC","In"],"name":"Camera Movement","time":74237.2881355932},{"params":["quint","Out","0.01","0.7"],"time":74237.2881355932,"name":"Cam Zoom"},{"params":[0.01,"camGame"],"time":74237.2881355932,"name":"Add Camera Zoom"},{"params":["quad","Out","1","1.4"],"time":74237.2881355932,"name":"Beat Flash"},{"params":[0,false,4,"CLASSIC","In"],"name":"Camera Movement","time":74745.7627118644},{"params":[false,0.4,"camGame",4,"linear","In","direct",false],"time":74745.7627118644,"name":"Camera Zoom"},{"params":[0.01,"camGame"],"time":74745.7627118644,"name":"Add Camera Zoom"},{"params":["quad","Out","1","1.4"],"time":74745.7627118644,"name":"Beat Flash"},{"params":[1,false,4,"CLASSIC","In"],"name":"Camera Movement","time":75254.2372881356},{"params":[false,0.7,"camGame",4,"linear","In","direct",false],"time":75254.2372881356,"name":"Camera Zoom"},{"params":["quad","Out","1","1.4"],"time":75254.2372881356,"name":"Beat Flash"},{"params":["quad","Out","1","1.4"],"name":"Beat Flash","time":75762.7118644068},{"params":[0.01,"camGame"],"name":"Add Camera Zoom","time":75762.7118644068},{"params":[615,60,false,4,"CLASSIC","In",false],"time":76271.186440678,"name":"Camera Position"},{"params":[false,0.4,"camGame",4,"linear","In","direct",false],"time":76271.186440678,"name":"Camera Zoom"},{"params":[0.01,"camGame"],"time":76271.186440678,"name":"Add Camera Zoom"},{"params":["quad","Out","1","1.4"],"time":76271.186440678,"name":"Beat Flash"},{"params":["quad","Out","1","1.4"],"time":76779.6610169491,"name":"Beat Flash"},{"params":[0.01,"camGame"],"time":76779.6610169491,"name":"Add Camera Zoom"},{"params":[0,true,4,"CLASSIC","In"],"name":"Camera Movement","time":77288.1355932203},{"params":[true,0.5,"camGame",4,"quint","Out","direct",false],"time":77288.1355932203,"name":"Camera Zoom"},{"params":["quad","Out","1","1.4"],"time":77288.1355932203,"name":"Beat Flash"},{"params":["quad","Out","1","1.4"],"name":"Beat Flash","time":77796.6101694915},{"params":[0.01,"camGame"],"name":"Add Camera Zoom","time":77796.6101694915},{"params":["quad","Out","1","1.4"],"time":78305.0847457627,"name":"Beat Flash"},{"params":[0.01,"camGame"],"time":78305.0847457627,"name":"Add Camera Zoom"},{"params":["quad","Out","1","1.4"],"name":"Beat Flash","time":78813.5593220339},{"params":[0.01,"camGame"],"name":"Add Camera Zoom","time":78813.5593220339},{"params":[1,false,4,"CLASSIC","In"],"time":79322.0338983051,"name":"Camera Movement"},{"params":[false,0.7,"camGame",4,"quint","Out","direct",false],"time":79322.0338983051,"name":"Camera Zoom"},{"params":["quad","Out","1","1.4"],"time":79322.0338983051,"name":"Beat Flash"},{"params":["quad","Out","1","1.4"],"time":79830.5084745763,"name":"Beat Flash"},{"params":[0.01,"camGame"],"time":79830.5084745763,"name":"Add Camera Zoom"},{"params":[true,0.68,"camGame",4,"quint","Out","direct",false],"time":80338.9830508475,"name":"Camera Zoom"},{"params":[0.01,"camGame"],"time":80338.9830508475,"name":"Add Camera Zoom"},{"params":["quad","Out","1","1.4"],"time":80338.9830508475,"name":"Beat Flash"},{"params":[-16777216,"0.01",true,"camGame"],"time":80847.4576271186,"name":"fade"},{"params":["0.01",false,false,true,false,false,"back","In"],"time":80847.4576271186,"name":"Bar Cinematic"},{"params":[-16777216,"1",false,"camGame"],"name":"fade","time":81355.9322033898},{"params":[0,false,4,"CLASSIC","In"],"time":81355.9322033898,"name":"Camera Movement"},{"params":["0.01",false,true,true,true,false,"back","In"],"time":81355.9322033898,"name":"Bar Cinematic"},{"params":[false,0.4,"camGame",8,"linear","In","direct",false],"time":81355.9322033898,"name":"Camera Zoom"},{"params":[1,true,4,"CLASSIC","In"],"name":"Camera Movement","time":89491.5254237288},{"params":[true,0.7,"camGame",8,"quint","Out","direct",false],"time":89491.5254237288,"name":"Camera Zoom"},{"params":[0,true,4,"CLASSIC","In"],"name":"Camera Movement","time":97627.1186440678},{"params":[true,3,4,"linear","In",false],"name":"Scroll Speed Change","time":97627.1186440678},{"params":[true,0.4,"camGame",4,"quint","Out","direct",false],"time":97627.1186440678,"name":"Camera Zoom"},{"params":["1",false,false,false,false,false,"expo","Out"],"time":97627.1186440678,"name":"Bar Cinematic"},{"params":["quad","Out","1","1.4"],"name":"Beat Flash","time":98644.0677966102},{"params":[0.01,"camGame"],"name":"Add Camera Zoom","time":98644.0677966102},{"params":["quad","Out","1","1.4"],"time":99406.7796610169,"name":"Beat Flash"},{"params":[0.01,"camGame"],"time":99406.7796610169,"name":"Add Camera Zoom"},{"params":["quad","Out","1","1.4"],"name":"Beat Flash","time":100042.372881356},{"params":[0.01,"camGame"],"name":"Add Camera Zoom","time":100042.372881356},{"params":["quad","Out","1","1.4"],"time":100677.966101695,"name":"Beat Flash"},{"params":[0.01,"camGame"],"time":100677.966101695,"name":"Add Camera Zoom"},{"params":["quad","Out","1","1.4"],"time":101186.440677966,"name":"Beat Flash"},{"params":[0.01,"camGame"],"time":101186.440677966,"name":"Add Camera Zoom"},{"params":["quad","Out","1","1.4"],"time":101440.677966102,"name":"Beat Flash"},{"params":[0.01,"camGame"],"time":101440.677966102,"name":"Add Camera Zoom"},{"params":["quad","Out","1","1.4"],"name":"Beat Flash","time":102203.389830508},{"params":[0.01,"camGame"],"name":"Add Camera Zoom","time":102203.389830508},{"params":["quad","Out","1","1.4"],"name":"Beat Flash","time":102711.86440678},{"params":[0.01,"camGame"],"name":"Add Camera Zoom","time":102711.86440678},{"params":["quad","Out","1","1.4"],"name":"Beat Flash","time":103220.338983051},{"params":[0.01,"camGame"],"name":"Add Camera Zoom","time":103220.338983051},{"params":["quad","Out","1","1.4"],"name":"Beat Flash","time":103474.576271186},{"params":[0.01,"camGame"],"name":"Add Camera Zoom","time":103474.576271186},{"params":["quint","Out","2","0.45"],"time":103728.813559322,"name":"Cam Zoom"},{"params":["quad","Out","1","1.4"],"time":104110.169491525,"name":"Beat Flash"},{"params":[0.01,"camGame"],"time":104110.169491525,"name":"Add Camera Zoom"},{"params":["quad","Out","1","1.4"],"name":"Beat Flash","time":104872.881355932},{"params":[0.01,"camGame"],"name":"Add Camera Zoom","time":104872.881355932},{"params":["quad","Out","1","1.4"],"time":105254.237288136,"name":"Beat Flash"},{"params":[0.01,"camGame"],"time":105254.237288136,"name":"Add Camera Zoom"},{"params":["quad","Out","1","1.4"],"name":"Beat Flash","time":105508.474576271},{"params":[0.01,"camGame"],"name":"Add Camera Zoom","time":105508.474576271},{"params":["quad","Out","1","1.4"],"time":105635.593220339,"name":"Beat Flash"},{"params":[0.01,"camGame"],"time":105635.593220339,"name":"Add Camera Zoom"},{"params":[false,-63994,4,"camHUD"],"time":105762.711864407,"name":"Camera Flash"},{"params":[0,"scream",true,"NONE"],"name":"Play Animation","time":105762.711864407},{"params":["quint","Out","1","0.4"],"time":105762.711864407,"name":"Cam Zoom"},{"params":["0.005","1"],"time":105762.711864407,"name":"Shake"},{"params":[1,true,4,"CLASSIC","In"],"time":106779.661016949,"name":"Camera Movement"},{"params":["quint","Out","1","0.7"],"time":106779.661016949,"name":"Cam Zoom"},{"params":[0.01,"camGame"],"time":106779.661016949,"name":"Add Camera Zoom"},{"params":["quad","Out","1","1.4"],"time":106779.661016949,"name":"Beat Flash"},{"params":["quad","Out","1","1.4"],"time":107542.372881356,"name":"Beat Flash"},{"params":[0.01,"camGame"],"time":107542.372881356,"name":"Add Camera Zoom"},{"params":["quad","Out","1","1.4"],"name":"Beat Flash","time":108177.966101695},{"params":[0.01,"camGame"],"name":"Add Camera Zoom","time":108177.966101695},{"params":["quad","Out","1","1.4"],"time":108813.559322034,"name":"Beat Flash"},{"params":[0.01,"camGame"],"time":108813.559322034,"name":"Add Camera Zoom"},{"params":["quad","Out","1","1.4"],"name":"Beat Flash","time":109576.271186441},{"params":[0.01,"camGame"],"name":"Add Camera Zoom","time":109576.271186441},{"params":["quad","Out","1","1.4"],"time":110847.457627119,"name":"Beat Flash"},{"params":[0.01,"camGame"],"time":110847.457627119,"name":"Add Camera Zoom"},{"params":["quad","Out","1","1.4"],"name":"Beat Flash","time":111355.93220339},{"params":[0.01,"camGame"],"name":"Add Camera Zoom","time":111355.93220339},{"params":["quad","Out","1","1.4"],"name":"Beat Flash","time":111610.169491525},{"params":[0.01,"camGame"],"name":"Add Camera Zoom","time":111610.169491525},{"params":["quad","Out","1","1.4"],"time":112245.762711864,"name":"Beat Flash"},{"params":[0.01,"camGame"],"time":112245.762711864,"name":"Add Camera Zoom"},{"params":["quad","Out","1","1.4"],"name":"Beat Flash","time":113008.474576271},{"params":[0.01,"camGame"],"name":"Add Camera Zoom","time":113008.474576271},{"params":["quad","Out","1","1.4"],"time":113389.830508475,"name":"Beat Flash"},{"params":[0.01,"camGame"],"time":113389.830508475,"name":"Add Camera Zoom"},{"params":["quad","Out","1","1.4"],"name":"Beat Flash","time":113644.06779661},{"params":[0.01,"camGame"],"name":"Add Camera Zoom","time":113644.06779661},{"params":["quad","Out","1","1.4"],"time":113771.186440678,"name":"Beat Flash"},{"params":[0.01,"camGame"],"time":113771.186440678,"name":"Add Camera Zoom"},{"params":[0,true,4,"CLASSIC","In"],"time":113898.305084746,"name":"Camera Movement"},{"params":[false,-1,8,"camGame"],"time":113898.305084746,"name":"Camera Flash"},{"params":["quint","Out","1","0.4"],"time":113898.305084746,"name":"Cam Zoom"},{"params":["quad","Out","1","1.4"],"name":"Beat Flash","time":114406.779661017},{"params":[0.01,"camGame"],"name":"Add Camera Zoom","time":114406.779661017},{"params":["quad","Out","1","1.4"],"name":"Beat Flash","time":114915.254237288},{"params":[0.01,"camGame"],"name":"Add Camera Zoom","time":114915.254237288},{"params":["quad","Out","1","1.4"],"time":115423.728813559,"name":"Beat Flash"},{"params":[0.01,"camGame"],"time":115423.728813559,"name":"Add Camera Zoom"},{"params":["quad","Out","1","1.4"],"time":115932.203389831,"name":"Beat Flash"},{"params":["quad","Out","1","1.4"],"name":"Beat Flash","time":116440.677966102},{"params":[0.01,"camGame"],"name":"Add Camera Zoom","time":116440.677966102},{"params":["quad","Out","1","1.4"],"time":116949.152542373,"name":"Beat Flash"},{"params":[0.01,"camGame"],"time":116949.152542373,"name":"Add Camera Zoom"},{"params":["quad","Out","1","1.4"],"time":117457.627118644,"name":"Beat Flash"},{"params":[0.01,"camGame"],"time":117457.627118644,"name":"Add Camera Zoom"},{"params":[1,true,24,"CLASSIC","Out"],"time":117966.101694915,"name":"Camera Movement"},{"params":["quint","Out","1","0.7"],"time":117966.101694915,"name":"Cam Zoom"},{"params":["quad","Out","1","1.4"],"time":117966.101694915,"name":"Beat Flash"},{"params":["quad","Out","1","1.4"],"name":"Beat Flash","time":118474.576271186},{"params":[0.01,"camGame"],"name":"Add Camera Zoom","time":118474.576271186},{"params":["quad","Out","1","1.4"],"time":118983.050847458,"name":"Beat Flash"},{"params":[0.01,"camGame"],"time":118983.050847458,"name":"Add Camera Zoom"},{"params":["quad","Out","1","1.4"],"time":119491.525423729,"name":"Beat Flash"},{"params":[0.01,"camGame"],"time":119491.525423729,"name":"Add Camera Zoom"},{"params":["quad","Out","1","1.4"],"name":"Beat Flash","time":120000},{"params":["quad","Out","1","1.4"],"name":"Beat Flash","time":120508.474576271},{"params":[0.01,"camGame"],"name":"Add Camera Zoom","time":120508.474576271},{"params":["quad","Out","1","1.4"],"name":"Beat Flash","time":121016.949152542},{"params":[0.01,"camGame"],"name":"Add Camera Zoom","time":121016.949152542},{"params":["quad","Out","1","1.4"],"time":121525.423728814,"name":"Beat Flash"},{"params":[0.01,"camGame"],"time":121525.423728814,"name":"Add Camera Zoom"},{"params":["quint","Out","1","0.4"],"time":122033.898305085,"name":"Cam Zoom"},{"params":[615,60,true,4,"CLASSIC","In",false],"time":122033.898305085,"name":"Camera Position"},{"params":["quad","Out","1","1.4"],"time":122033.898305085,"name":"Beat Flash"},{"params":["quint","Out","1","0.45"],"time":122542.372881356,"name":"Cam Zoom"},{"params":[0.01,"camGame"],"time":122542.372881356,"name":"Add Camera Zoom"},{"params":["quad","Out","1","1.4"],"time":122542.372881356,"name":"Beat Flash"},{"params":["quint","Out","1","0.425 "],"name":"Cam Zoom","time":123050.847457627},{"params":["quint","Out","1","0.4"],"time":123559.322033898,"name":"Cam Zoom"},{"params":[0.01,"camGame"],"time":123559.322033898,"name":"Add Camera Zoom"},{"params":["quad","Out","1","1.4"],"time":123559.322033898,"name":"Beat Flash"},{"params":["quint","Out","1","0.45"],"time":124576.271186441,"name":"Cam Zoom"},{"params":["quad","Out","1","1.4"],"time":124576.271186441,"name":"Beat Flash"},{"params":[0.01,"camGame"],"time":124576.271186441,"name":"Add Camera Zoom"},{"params":["quint","Out","1","0.425"],"name":"Cam Zoom","time":125084.745762712},{"params":["quint","Out","1","0.4"],"name":"Cam Zoom","time":125593.220338983},{"params":[0.01,"camGame"],"time":125593.220338983,"name":"Add Camera Zoom"},{"params":["quad","Out","1","1.4"],"time":125593.220338983,"name":"Beat Flash"},{"params":[0,true,12,"quint","Out"],"time":126101.694915254,"name":"Camera Movement"},{"params":["quad","Out","1","1.4"],"name":"Beat Flash","time":126610.169491525},{"params":[0.01,"camGame"],"name":"Add Camera Zoom","time":126610.169491525},{"params":["quad","Out","1","1.4"],"time":127118.644067797,"name":"Beat Flash"},{"params":[0.01,"camGame"],"time":127118.644067797,"name":"Add Camera Zoom"},{"params":["quad","Out","1","1.4"],"time":127627.118644068,"name":"Beat Flash"},{"params":[0.01,"camGame"],"time":127627.118644068,"name":"Add Camera Zoom"},{"params":["quad","Out","1","1.4"],"time":128135.593220339,"name":"Beat Flash"},{"params":["quad","Out","1","1.4"],"name":"Beat Flash","time":128644.06779661},{"params":[0.01,"camGame"],"name":"Add Camera Zoom","time":128644.06779661},{"params":[-16777216,"0.01",true,"camGame"],"time":129661.016949153,"name":"fade"},{"params":[1,true,64,"sine","Out"],"time":130169.491525424,"name":"Camera Movement"},{"params":["quad","Out","4","0.2"],"time":130169.491525424,"name":"black disto 2"},{"params":["4",false,true,true,true,false,"quad","InOut"],"time":130169.491525424,"name":"Bar Cinematic"},{"params":[-1,"1",false,"camGame"],"time":130169.491525424,"name":"fade"},{"params":[true,0.7,"camGame",64,"sine","Out","direct",false],"time":130169.491525424,"name":"Camera Zoom"},{"params":["quad","Out","1","1.4"],"time":130677.966101695,"name":"Beat Flash"},{"params":[0.01,"camGame"],"time":130677.966101695,"name":"Add Camera Zoom"},{"params":["quad","Out","1","1.4"],"time":131186.440677966,"name":"Beat Flash"},{"params":[0.01,"camGame"],"time":131186.440677966,"name":"Add Camera Zoom"},{"params":["quad","Out","1","1.4"],"name":"Beat Flash","time":131694.915254237},{"params":[0.01,"camGame"],"name":"Add Camera Zoom","time":131694.915254237},{"params":["quad","Out","1","1.4"],"time":132203.389830508,"name":"Beat Flash"},{"params":["quad","Out","1","1.4"],"time":132711.86440678,"name":"Beat Flash"},{"params":[0.01,"camGame"],"time":132711.86440678,"name":"Add Camera Zoom"},{"params":["quad","Out","1","1.4"],"name":"Beat Flash","time":133220.338983051},{"params":[0.01,"camGame"],"name":"Add Camera Zoom","time":133220.338983051},{"params":["quad","Out","1","1.4"],"name":"Beat Flash","time":133728.813559322},{"params":[0.01,"camGame"],"name":"Add Camera Zoom","time":133728.813559322},{"params":["quint","Out","1","0.725"],"time":134237.288135593,"name":"Cam Zoom"},{"params":["quad","Out","1","1.4"],"time":134237.288135593,"name":"Beat Flash"},{"params":["quad","Out","1","1.4"],"time":134745.762711864,"name":"Beat Flash"},{"params":[0.01,"camGame"],"time":134745.762711864,"name":"Add Camera Zoom"},{"params":["quad","Out","1","1.4"],"name":"Beat Flash","time":135254.237288136},{"params":[0.01,"camGame"],"name":"Add Camera Zoom","time":135254.237288136},{"params":["quad","Out","1","1.4"],"time":135762.711864407,"name":"Beat Flash"},{"params":[0.01,"camGame"],"time":135762.711864407,"name":"Add Camera Zoom"},{"params":["quad","Out","1","1.4"],"name":"Beat Flash","time":136779.661016949},{"params":[0.01,"camGame"],"name":"Add Camera Zoom","time":136779.661016949},{"params":["quad","Out","1","1.4"],"time":137288.13559322,"name":"Beat Flash"},{"params":[0.01,"camGame"],"time":137288.13559322,"name":"Add Camera Zoom"},{"params":["quint","Out","1","0.675"],"name":"Cam Zoom","time":137796.610169492},{"params":[0.01,"camGame"],"time":137796.610169492,"name":"Add Camera Zoom"},{"params":["quad","Out","1","1.4"],"time":137796.610169492,"name":"Beat Flash"},{"params":["quint","Out","1","0.7"],"time":138305.084745763,"name":"Cam Zoom"},{"params":["quad","Out","1","1.4"],"name":"Beat Flash","time":138813.559322034},{"params":[0.01,"camGame"],"name":"Add Camera Zoom","time":138813.559322034},{"params":["quad","Out","1","1.4"],"time":139322.033898305,"name":"Beat Flash"},{"params":[0.01,"camGame"],"time":139322.033898305,"name":"Add Camera Zoom"},{"params":["quad","Out","1","1.4"],"name":"Beat Flash","time":139830.508474576},{"params":[0.01,"camGame"],"name":"Add Camera Zoom","time":139830.508474576},{"params":["quint","Out","1","0.725"],"time":140338.983050847,"name":"Cam Zoom"},{"params":["quad","Out","1","1.4"],"time":140847.457627119,"name":"Beat Flash"},{"params":[0.01,"camGame"],"time":140847.457627119,"name":"Add Camera Zoom"},{"params":["quad","Out","1","1.4"],"name":"Beat Flash","time":141355.93220339},{"params":[0.01,"camGame"],"name":"Add Camera Zoom","time":141355.93220339},{"params":["quad","Out","1","1.4"],"time":141864.406779661,"name":"Beat Flash"},{"params":[0.01,"camGame"],"time":141864.406779661,"name":"Add Camera Zoom"},{"params":["quint","Out","1","0.75"],"time":142372.881355932,"name":"Cam Zoom"},{"params":["quad","Out","1","1.4"],"time":142372.881355932,"name":"Beat Flash"},{"params":["quad","Out","1","1.4"],"name":"Beat Flash","time":142881.355932203},{"params":[0.01,"camGame"],"name":"Add Camera Zoom","time":142881.355932203},{"params":["quad","Out","1","1.4"],"time":143389.830508475,"name":"Beat Flash"},{"params":[0.01,"camGame"],"time":143389.830508475,"name":"Add Camera Zoom"},{"params":["quad","Out","1","1.4"],"name":"Beat Flash","time":143898.305084746},{"params":[0.01,"camGame"],"name":"Add Camera Zoom","time":143898.305084746},{"params":["quint","Out","1","0.7"],"name":"Cam Zoom","time":144406.779661017},{"params":["quad","Out","1","1.4"],"time":144406.779661017,"name":"Beat Flash"},{"params":["sine","Out","1","0.3"],"time":144406.779661017,"name":"black disto 2"},{"params":[0,true,8,"expo","In"],"time":145423.728813559,"name":"Camera Movement"},{"params":[true,0.4,"camGame",8,"expo","In","direct",false],"time":145423.728813559,"name":"Camera Zoom"},{"params":["quad","Out","1","1.4"],"time":146440.677966102,"name":"Beat Flash"},{"params":[false,-1,4,"camGame"],"time":146440.677966102,"name":"Camera Flash"},{"params":["sine","Out","1","0"],"time":146440.677966102,"name":"black disto 2"},{"params":["3",false,false,false,false,false,"expo","Out"],"time":146440.677966102,"name":"Bar Cinematic"},{"params":["quad","Out","1","1.4"],"time":146949.152542373,"name":"Beat Flash"},{"params":[0.01,"camGame"],"time":146949.152542373,"name":"Add Camera Zoom"},{"params":["quad","Out","1","1.4"],"name":"Beat Flash","time":147457.627118644},{"params":[0.01,"camGame"],"name":"Add Camera Zoom","time":147457.627118644},{"params":["quad","Out","1","1.4"],"time":147966.101694915,"name":"Beat Flash"},{"params":[0.01,"camGame"],"time":147966.101694915,"name":"Add Camera Zoom"},{"params":["quint","Out","1","0.425"],"name":"Cam Zoom","time":148474.576271186},{"params":["quad","Out","1","1.4"],"time":148474.576271186,"name":"Beat Flash"},{"params":["quad","Out","1","1.4"],"name":"Beat Flash","time":148983.050847458},{"params":[0.01,"camGame"],"name":"Add Camera Zoom","time":148983.050847458},{"params":["quad","Out","1","1.4"],"time":149491.525423729,"name":"Beat Flash"},{"params":[0.01,"camGame"],"time":149491.525423729,"name":"Add Camera Zoom"},{"params":["quad","Out","1","1.4"],"name":"Beat Flash","time":150000},{"params":[0.01,"camGame"],"name":"Add Camera Zoom","time":150000},{"params":["quint","Out","1","0.45"],"time":150508.474576271,"name":"Cam Zoom"},{"params":["quad","Out","1","1.4"],"time":150508.474576271,"name":"Beat Flash"},{"params":["quad","Out","1","1.4"],"time":151016.949152542,"name":"Beat Flash"},{"params":[0.01,"camGame"],"time":151016.949152542,"name":"Add Camera Zoom"},{"params":["quad","Out","1","1.4"],"name":"Beat Flash","time":151525.423728814},{"params":[0.01,"camGame"],"name":"Add Camera Zoom","time":151525.423728814},{"params":["quad","Out","1","1.4"],"time":152033.898305085,"name":"Beat Flash"},{"params":[0.01,"camGame"],"time":152033.898305085,"name":"Add Camera Zoom"},{"params":["quint","Out","1","0.475"],"name":"Cam Zoom","time":152542.372881356},{"params":["quad","Out","1","1.4"],"time":152542.372881356,"name":"Beat Flash"},{"params":["quad","Out","1","1.4"],"name":"Beat Flash","time":153050.847457627},{"params":[0.01,"camGame"],"name":"Add Camera Zoom","time":153050.847457627},{"params":["quint","Out","1","0.425"],"name":"Cam Zoom","time":153559.322033898},{"params":[0.01,"camGame"],"time":153559.322033898,"name":"Add Camera Zoom"},{"params":["quad","Out","1","1.4"],"time":153559.322033898,"name":"Beat Flash"},{"params":["quad","Out","1","1.4"],"time":154067.796610169,"name":"Beat Flash"},{"params":[0.01,"camGame"],"time":154067.796610169,"name":"Add Camera Zoom"},{"params":["quint","Out","1","0.4"],"time":154067.796610169,"name":"Cam Zoom"},{"params":[1,false,1,"CLASSIC","In"],"time":154576.271186441,"name":"Camera Movement"},{"params":["quint","Out","0.01","0.7"],"time":154576.271186441,"name":"Cam Zoom"},{"params":["quad","Out","1","1.4"],"time":154576.271186441,"name":"Beat Flash"},{"params":["quad","Out","1","1.4"],"name":"Beat Flash","time":155084.745762712},{"params":[0.01,"camGame"],"name":"Add Camera Zoom","time":155084.745762712},{"params":["quad","Out","1","1.4"],"time":155593.220338983,"name":"Beat Flash"},{"params":[0.01,"camGame"],"time":155593.220338983,"name":"Add Camera Zoom"},{"params":["quad","Out","1","1.4"],"name":"Beat Flash","time":156101.694915254},{"params":[0.01,"camGame"],"name":"Add Camera Zoom","time":156101.694915254},{"params":["quint","Out","1","0.725"],"time":156610.169491525,"name":"Cam Zoom"},{"params":["quad","Out","1","1.4"],"time":156610.169491525,"name":"Beat Flash"},{"params":["quad","Out","1","1.4"],"time":157118.644067797,"name":"Beat Flash"},{"params":[0.01,"camGame"],"time":157118.644067797,"name":"Add Camera Zoom"},{"params":["quad","Out","1","1.4"],"name":"Beat Flash","time":157627.118644068},{"params":[0.01,"camGame"],"name":"Add Camera Zoom","time":157627.118644068},{"params":["quad","Out","1","1.4"],"time":158135.593220339,"name":"Beat Flash"},{"params":[0.01,"camGame"],"time":158135.593220339,"name":"Add Camera Zoom"},{"params":["quint","Out","1","0.75"],"name":"Cam Zoom","time":158644.06779661},{"params":["quad","Out","1","1.4"],"time":158644.06779661,"name":"Beat Flash"},{"params":["quad","Out","1","1.4"],"name":"Beat Flash","time":159152.542372881},{"params":[0.01,"camGame"],"name":"Add Camera Zoom","time":159152.542372881},{"params":["quad","Out","1","1.4"],"time":159661.016949153,"name":"Beat Flash"},{"params":[0.01,"camGame"],"time":159661.016949153,"name":"Add Camera Zoom"},{"params":["quad","Out","1","1.4"],"name":"Beat Flash","time":160169.491525424},{"params":[0.01,"camGame"],"name":"Add Camera Zoom","time":160169.491525424},{"params":["quint","Out","3","0.775"],"time":160677.966101695,"name":"Cam Zoom"},{"params":["sine","Out","1","0.3"],"time":160677.966101695,"name":"black disto 2"},{"params":[-16777216,"0.5",true,"camHUD"],"time":162203.389830508,"name":"fade"},{"params":[-1,"1",false,"camHUD"],"time":162711.86440678,"name":"fade"},{"params":["5",false,true,true,false,false,"expo","Out"],"time":162711.86440678,"name":"Bar Cinematic"},{"params":[0,false,4,"CLASSIC","In"],"time":162711.86440678,"name":"Camera Movement"},{"params":["quint","Out","0.01","0.4"],"time":162711.86440678,"name":"Cam Zoom"},{"params":[1,true,32,"sine","InOut"],"time":170847.457627119,"name":"Camera Movement"},{"params":[true,0.7,"camGame",48,"sine","InOut","direct",false],"time":170847.457627119,"name":"Camera Zoom"},{"params":[0,true,24,"sine","InOut"],"time":174915.254237288,"name":"Camera Movement"},{"params":[true,0.4,"camGame",24,"sine","InOut","direct",false],"time":174915.254237288,"name":"Camera Zoom"},{"params":[0,"scream",true,"NONE"],"name":"Play Animation","time":177966.101694915},{"params":[false,-65536,4,"camHUD"],"time":177966.101694915,"name":"Camera Flash"},{"params":["sine","Out","0.01","0"],"time":177966.101694915,"name":"black disto 2"},{"params":["0.1",false,false,true,false,false,"quart","Out"],"time":177966.101694915,"name":"Bar Cinematic"},{"params":["0.01","2"],"time":177966.101694915,"name":"Shake"},{"params":[false,-65536,4,"camHUD"],"time":178983.050847458,"name":"Camera Flash"},{"params":["quint","Out","1","0.4"],"time":178983.050847458,"name":"Cam Zoom"},{"params":["quad","Out","1","1.4"],"time":178983.050847458,"name":"Beat Flash"},{"params":["1",false,false,false,false,false,"back","In"],"time":178983.050847458,"name":"Bar Cinematic"},{"params":[1,true,24,"CLASSIC","Out"],"time":183050.847457627,"name":"Camera Movement"},{"params":["quint","Out","1","0.7"],"name":"Cam Zoom","time":183050.847457627},{"params":[0,true,4,"CLASSIC","In"],"time":187118.644067797,"name":"Camera Movement"},{"params":["quint","Out","1","0.4"],"name":"Cam Zoom","time":187118.644067797},{"params":[1,true,4,"CLASSIC","In"],"time":191186.440677966,"name":"Camera Movement"},{"params":["quint","Out","1","0.7"],"name":"Cam Zoom","time":191186.440677966},{"params":["quint","Out","1","0.675"],"name":"Cam Zoom","time":192203.389830508},{"params":["quint","Out","1","0.65"],"time":193220.338983051,"name":"Cam Zoom"},{"params":["quint","Out","0.75","0.8"],"name":"Cam Zoom","time":194237.288135593},{"params":[-16777216,"0.01",true,"camGame"],"time":194237.288135593,"name":"fade"},{"params":["quint","Out","1","1"],"time":194745.762711864,"name":"Cam Zoom"},{"params":[0,false,1,"CLASSIC","In"],"time":195254.237288136,"name":"Camera Movement"},{"params":[false,-10158008,4,"camHUD"],"time":195254.237288136,"name":"Camera Flash"},{"params":["2",false,true,true,true,false,"quint","In"],"time":195254.237288136,"name":"Bar Cinematic"},{"params":["sine","Out","0.01","0.5"],"time":195254.237288136,"name":"black disto 2"},{"params":["quint","Out","0.01","0.4"],"time":195254.237288136,"name":"Cam Zoom"},{"params":[-65536,"1",false,"camGame"],"time":195254.237288136,"name":"fade"},{"params":[0.01,"camGame"],"time":196016.949152542,"name":"Add Camera Zoom"},{"params":[0.02,"camGame"],"time":198050.847457627,"name":"Add Camera Zoom"},{"params":[1,false,12,"CLASSIC","In"],"name":"Camera Movement","time":199322.033898305},{"params":[false,0.7,"camGame",4,"linear","In","direct",false],"time":199322.033898305,"name":"Camera Zoom"},{"params":[0.02,"camGame"],"name":"Add Camera Zoom","time":200084.745762712},{"params":[0.02,"camGame"],"time":202118.644067797,"name":"Add Camera Zoom"},{"params":[0,false,12,"CLASSIC","In"],"name":"Camera Movement","time":203389.830508475},{"params":[false,0.4,"camGame",4,"linear","In","direct",false],"time":203389.830508475,"name":"Camera Zoom"},{"params":[0.02,"camGame"],"name":"Add Camera Zoom","time":204152.542372881},{"params":[0.02,"camGame"],"time":206186.440677966,"name":"Add Camera Zoom"},{"params":[1,false,12,"quad","In"],"name":"Camera Movement","time":207457.627118644},{"params":[false,0.7,"camGame",4,"linear","In","direct",false],"time":207457.627118644,"name":"Camera Zoom"},{"params":[0.02,"camGame"],"name":"Add Camera Zoom","time":208220.338983051},{"params":["quint","Out","2","0.725"],"name":"Cam Zoom","time":209491.525423729},{"params":[0.02,"camGame"],"time":210254.237288136,"name":"Add Camera Zoom"},{"params":[0,true,4,"CLASSIC","In"],"name":"Camera Movement","time":211525.423728814},{"params":[false,-4980736,4,"camHUD"],"time":211525.423728814,"name":"Camera Flash"},{"params":["5",false,false,false,false,false,"expo","Out"],"time":211525.423728814,"name":"Bar Cinematic"},{"params":["quint","Out","1","0.4"],"time":211525.423728814,"name":"Cam Zoom"},{"params":["sine","Out","1","0"],"time":211525.423728814,"name":"black disto 2"},{"params":["0.005","0.5"],"time":212542.372881356,"name":"Shake"},{"params":["0.005","0.5"],"name":"Shake","time":213050.847457627},{"params":["0.005","0.5"],"time":214322.033898305,"name":"Shake"},{"params":["0.005","0.5"],"name":"Shake","time":215084.745762712},{"params":["0.005","0.25"],"time":215974.576271186,"name":"Shake"},{"params":["0.005","0.25"],"name":"Shake","time":216737.288135593},{"params":["0.005","0.25"],"time":216991.525423729,"name":"Shake"},{"params":["0.005","0.25"],"name":"Shake","time":217372.881355932},{"params":["0.005","0.25"],"time":218389.830508475,"name":"Shake"},{"params":["0.005","0.25"],"name":"Shake","time":218898.305084746},{"params":["0.005","0.25"],"time":219152.542372881,"name":"Shake"},{"params":["0.005","0.25"],"name":"Shake","time":219406.779661017},{"params":[1,true,4,"CLASSIC","In"],"name":"Camera Movement","time":219661.016949153},{"params":[true,0.7,"camGame",4,"quint","Out","direct",false],"time":219661.016949153,"name":"Camera Zoom"},{"params":["quint","Out","1","0.725"],"time":221694.915254237,"name":"Cam Zoom"},{"params":["quint","Out","0.75","0.75"],"name":"Cam Zoom","time":223728.813559322},{"params":[0,true,4,"CLASSIC","In"],"name":"Camera Movement","time":225762.711864407},{"params":["quint","Out","1","0.4"],"name":"Cam Zoom","time":225762.711864407},{"params":["0.01","2"],"time":226779.661016949,"name":"Shake"},{"params":["0.1",false,false,false,false,false,"quad","Out"],"time":226779.661016949,"name":"Bar Cinematic"},{"params":[false,-65536,4,"camHUD"],"time":226779.661016949,"name":"Camera Flash"},{"params":[0,true,4,"CLASSIC","In"],"time":227796.610169492,"name":"Camera Movement"},{"params":[false,-11534285,4,"camHUD"],"time":227796.610169492,"name":"Camera Flash"},{"params":["1",false,false,true,true,true,"sine","In"],"name":"Bar Cinematic","time":227796.610169492},{"params":["sine","InOut","17","0.35"],"name":"Cam Zoom","time":227796.610169492},{"params":[-16777216,"0.01",true,"camGame"],"name":"fade","time":244067.796610169}]}