{"events":[{"params":[1,true,4,"CLASSIC","In"],"name":"Camera Movement","time":0},{"params":[-16777216,"4",false,"camGame"],"time":0,"name":"fade"},{"params":[0],"name":"Camera Movement","time":9896.90721649485},{"params":[1],"name":"Camera Movement","time":14845.3608247423},{"params":[0],"name":"Camera Movement","time":17319.587628866},{"params":["sine","InOut","0.5","1.7"],"time":22286.25,"name":"Cam Zoom"},{"params":["quad","Out","1","1.6"],"time":22286.25,"name":"Beat Flash"},{"params":["sine","InOut","0.5","1.75"],"name":"Cam Zoom","time":25050},{"params":[1],"name":"Camera Movement","time":29690.7216494845},{"params":["sine","InOut","0.2","1"],"time":32159.9999999877,"name":"Cam Zoom"},{"params":[true,false,1],"time":32159.9999999877,"name":"Alt Animation Toggle"},{"params":["quad","Out","1","1.6"],"time":32159.9999999877,"name":"Beat Flash"},{"params":[false,false,1],"time":34800,"name":"Alt Animation Toggle"},{"params":["sine","InOut","0.5","1.1"],"name":"Cam Zoom","time":39000},{"params":[true,false,1],"time":39000,"name":"Alt Animation Toggle"},{"params":["sine","InOut","0.5","1.2"],"time":39300,"name":"Cam Zoom"},{"params":[0],"name":"Camera Movement","time":39587.6288659794},{"params":[false,false,1],"name":"Alt Animation Toggle","time":40800},{"params":[1],"name":"Camera Movement","time":44536.0824742268},{"params":[0],"name":"Camera Movement","time":49484.5360824742},{"params":[1],"name":"Camera Movement","time":51958.7628865979},{"params":[true,false,1],"time":51958.7628865979,"name":"Alt Animation Toggle"},{"params":[0],"name":"Camera Movement","time":54432.9896907217},{"params":[1],"name":"Camera Movement","time":59381.4432989691},{"params":[false,false,1],"time":59381.4432989691,"name":"Alt Animation Toggle"},{"params":[true,false,1],"time":61800,"name":"Alt Animation Toggle"},{"params":[false,false,1],"name":"Alt Animation Toggle","time":64200},{"params":[0],"name":"Camera Movement","time":64329.8969072165},{"params":[1],"name":"Camera Movement","time":65567.0103092784},{"params":[0],"name":"Camera Movement","time":66804.1237113402},{"params":[1],"name":"Camera Movement","time":69278.3505154639},{"params":["quad","Out","1","1.6"],"time":69278.3505154639,"name":"Beat Flash"},{"params":[0],"name":"Camera Movement","time":74226.8041237114},{"params":[1],"name":"Camera Movement","time":79175.2577319588},{"params":["quad","Out","1","1.6"],"time":79500,"name":"Beat Flash"},{"params":[true,false,1],"time":81600,"name":"Alt Animation Toggle"},{"params":[false,false,1],"name":"Alt Animation Toggle","time":82950},{"params":[true,false,1],"time":84150,"name":"Alt Animation Toggle"},{"params":[false,false,1],"name":"Alt Animation Toggle","time":85350},{"params":[true,false,1],"time":87900,"name":"Alt Animation Toggle"},{"params":[0],"name":"Camera Movement","time":89072.1649484537},{"params":[false,false,1],"name":"Alt Animation Toggle","time":91350},{"params":[1],"name":"Camera Movement","time":96494.8453608249},{"params":[0],"name":"Camera Movement","time":98969.0721649487},{"params":["quad","Out","1","1.6"],"time":98969.0721649487,"name":"Beat Flash"},{"params":[1],"name":"Camera Movement","time":108865.979381444},{"params":[0],"name":"Camera Movement","time":111340.206185567},{"params":[1],"name":"Camera Movement","time":112577.319587629},{"params":[0],"name":"Camera Movement","time":113814.432989691},{"params":["quad","Out","1","1.8"],"time":118800,"name":"Beat Flash"},{"params":[1],"name":"Camera Movement","time":123711.340206186},{"params":[0],"name":"Camera Movement","time":128659.793814433},{"params":[1],"name":"Camera Movement","time":133608.247422681},{"params":[true,false,1],"time":136050,"name":"Alt Animation Toggle"},{"params":[0],"name":"Camera Movement","time":138556.701030928},{"params":["quad","Out","1","1.6"],"time":138556.701030928,"name":"Beat Flash"},{"params":[false,false,1],"name":"Alt Animation Toggle","time":138750},{"params":["quad","Out","1","1.6"],"time":141000,"name":"Beat Flash"},{"params":[1],"name":"Camera Movement","time":148453.608247423},{"params":[true,false,1],"time":150900,"name":"Alt Animation Toggle"},{"params":["quad","Out","1","1.8"],"time":150900,"name":"Beat Flash"},{"params":[false,false,1],"name":"Alt Animation Toggle","time":153600},{"params":[true,false,1],"time":157200,"name":"Alt Animation Toggle"},{"params":[0],"name":"Camera Movement","time":158350.515463918},{"params":[true,3,2,"linear","In"],"time":158350.515463918,"name":"Scroll Speed Change"},{"params":[false,false,1],"name":"Alt Animation Toggle","time":160050},{"params":[true,false,1],"time":163200,"name":"Alt Animation Toggle"},{"params":[1],"name":"Camera Movement","time":163298.969072166},{"params":[false,false,1],"name":"Alt Animation Toggle","time":165600},{"params":[true,false,1],"time":168150,"name":"Alt Animation Toggle"},{"params":[0],"name":"Camera Movement","time":168247.422680413},{"params":[false,false,1],"name":"Alt Animation Toggle","time":169650},{"params":[1],"name":"Camera Movement","time":178144.329896908},{"params":[true,false,1],"time":179400,"name":"Alt Animation Toggle"},{"params":[false,false,1],"name":"Alt Animation Toggle","time":180600},{"params":[0],"name":"Camera Movement","time":183092.783505155},{"params":[1],"name":"Camera Movement","time":184329.896907217},{"params":[0],"name":"Camera Movement","time":185567.010309279},{"params":[1],"name":"Camera Movement","time":188041.237113403},{"params":[0],"name":"Camera Movement","time":192989.69072165},{"params":[1],"name":"Camera Movement","time":197938.144329898},{"params":[true,false,1],"time":200400,"name":"Alt Animation Toggle"},{"params":[false,false,1],"name":"Alt Animation Toggle","time":202800},{"params":[true,false,1],"time":205350,"name":"Alt Animation Toggle"},{"params":[0],"name":"Camera Movement","time":207835.051546393},{"params":[false,false,1],"name":"Alt Animation Toggle","time":210000},{"params":[1],"name":"Camera Movement","time":215257.731958764},{"params":[0],"name":"Camera Movement","time":217731.958762888},{"params":["quad","Out","1","1.8"],"time":217731.958762888,"name":"Beat Flash"},{"params":[1],"name":"Camera Movement","time":227628.865979382},{"params":[true,false,1],"time":234300,"name":"Alt Animation Toggle"},{"params":[0],"name":"Camera Movement","time":237525.773195877},{"params":[false,false,1],"name":"Alt Animation Toggle","time":238950},{"params":[1],"name":"Camera Movement","time":242474.226804125},{"params":[0],"name":"Camera Movement","time":247422.680412372},{"params":[1],"name":"Camera Movement","time":252371.13402062},{"params":[true,false,1],"time":254850,"name":"Alt Animation Toggle"},{"params":[0],"name":"Camera Movement","time":258556.701030929},{"params":["WHAA","1.6","","0","camGame",false,false,false,"ciel2",false,false],"time":259350,"name":"video event"},{"params":[0,"jump",false],"name":"Play Animation","time":259950},{"params":[0,"jump",true],"name":"Play Animation","time":260550},{"params":[0,"jump",true],"name":"Play Animation","time":261150},{"params":[0,"waaa",true],"name":"Play Animation","time":261600},{"params":["0.03","5"],"time":262350,"name":"Shake"},{"params":["sine","Out","1","2"],"time":262350,"name":"Cam Zoom"},{"params":[false,true,0],"name":"Alt Animation Toggle","time":262800}]}